[
  { "title": "مقدمة الكتاب", "page": 9 },
  { "title": "تقديم", "page": 13 },
  { "title": "لماذا اختيار حسين عطية شهيد", "page": 17 },
  { "title": "مقتطفات من سيرته العطرة", "page": 19 },
  { "title": "محطات على طريق الشهادة", "page": 21 },
  { "title": "الطفل المميز", "page": 23 },
  { "title": "قلب نذر نفسه للحق", "page": 25 },
  { "title": "راعي العوائل... وحامل الأمانة", "page": 28 },
  { "title": "بداية جيش الإمام المهدي", "page": 31 },
  { "title": "السباق في تلبية أوامر القائد", "page": 34 },
  { "title": "الأولوية للعقيدة قبل كل شيء", "page": 37 },
  { "title": "في الطوسي... كان أول الواقفين", "page": 39 },
  { "title": "الحمية لله", "page": 41 },
  { "title": "حين أرعب الأسد أعتى الجيوش", "page": 44 },
  { "title": "الإيمان أقوى من السلاح", "page": 47 },
  { "title": "قلبٌ يسع الفقراء", "page": 49 },
  { "title": "الأسير", "page": 52 },
  { "title": "الأمانة التي عبرت خطوط النار", "page": 54 },
  { "title": "الصبر على طريق الجهاد", "page": 58 },
  { "title": "البتيرة... نصرٌ من صبر", "page": 61 },
  { "title": "حيّ المعلمين", "page": 64 },
  { "title": "الصبر في درب الفداء", "page": 67 },
  { "title": "ابتغاء مرضاة الله", "page": 70 },
  { "title": "تحت راية الإيمان", "page": 72 },
  { "title": "كان لنا أباً", "page": 75 },
  { "title": "خادم الإمام الحسين (عليه السلام)", "page": 87 },
  { "title": "سفرة الحسين ممدودة", "page": 80 },
  { "title": "حرارة الإيمان", "page": 83 },
  { "title": "وفاء لا يعرف حداً", "page": 86 },
  { "title": "يد العطاء", "page": 88 },
  { "title": "سلاحان لا يفترقان", "page": 91 },
  { "title": "يخدم والناس نيام", "page": 94 },
  { "title": "حسينية شهداء جيش الإمام", "page": 96 },
  { "title": "القلب وطناً للسكينة", "page": 99 },
  { "title": "يد الرحمة", "page": 102 },
  { "title": "السابقون السابقون", "page": 105 },
  { "title": "الزهد بالوظيفة", "page": 107 },
  { "title": "الراتب الأخير", "page": 109 },
  { "title": "قائدٌ يعيش هموم جنوده", "page": 112 },
  { "title": "الأسلوب في كسب القلوب", "page": 114 },
  { "title": "إذا أنتم شبعتم... أنا أشبع", "page": 118 },
  { "title": "حين يتكلم البكاء", "page": 121 },
  { "title": "أرواح لا تعرف الراحة", "page": 123 },
  { "title": "السائرون في درب الاصطفاء", "page": 125 },
  { "title": "ولأماناتهم راعون", "page": 128 },
  { "title": "حاجاتهم خفيفة", "page": 130 },
  { "title": "لا تسيروا خلفي", "page": 133 },
  { "title": "روح القيادة", "page": 135 },
  { "title": "محاسبة النفس", "page": 137 },
  { "title": "السيد محمد الصدر هدانا", "page": 140 },
  { "title": "ترويض النفس استعداداً لنداء الحجة", "page": 142 },
  { "title": "الصديق الصادق", "page": 144 },
  { "title": "فراسة المؤمن", "page": 146 },
  { "title": "أثر الصلاة", "page": 148 },
  { "title": "المشروع الخالد", "page": 151 },
  { "title": "العمل مقرون بتوفيقه أفراده", "page": 154 },
  { "title": "يد بيد.. نصرة للوطن", "page": 156 },
  { "title": "الالتحاق والبركة في كل خطوة", "page": 158 },
  { "title": "عطاء بلا مقابل", "page": 160 },
  { "title": "حين يلتقي السلاح بالقلم", "page": 163 },
  { "title": "هيبة الإيمان", "page": 166 },
  { "title": "قلبي لم يطمئن", "page": 168 },
  { "title": "المسؤولية أمام الله", "page": 171 },
  { "title": "حاجات الناس من نعم الله", "page": 174 },
  { "title": "تنقضي الهموم عنده", "page": 177 },
  { "title": "طلبه لأجلهم", "page": 179 },
  { "title": "من منكم حسين عطية؟", "page": 181 },
  { "title": "روح الأخوة", "page": 184 },
  { "title": "الطريق إلى الله", "page": 186 },
  { "title": "فرص الطاعة", "page": 189 },
  { "title": "لا أرى الموت إلا سعادة", "page": 191 },
  { "title": "كفيل المجاهدين", "page": 194 },
  { "title": "صُنّاع القادة", "page": 196 },
  { "title": "عندما تنطق الأجهزة بلُغة العطاء", "page": 198 },
  { "title": "الحلال سر التوفيق", "page": 200 },
  { "title": "ما بيها مأذونية", "page": 203 },
  { "title": "من غسل ملابسي؟", "page": 206 },
  { "title": "الكتمان", "page": 208 },
  { "title": "سبعون محمل", "page": 211 },
  { "title": "لا أتاجر بسمعة آل الصدر", "page": 213 },
  { "title": "المسؤولية خدمة لا سلطة", "page": 216 },
  { "title": "الأمانة فوق الحاجة", "page": 218 },
  { "title": "وأفرغتُ فؤاده لحبك", "page": 220 },
  { "title": "بعيد عن صخب الدنيا", "page": 222 },
  { "title": "درس في التواضع", "page": 224 },
  { "title": "الأبوية", "page": 227 },
  { "title": "خفاء النية وجلاء المقام", "page": 229 },
  { "title": "القيم العليا", "page": 232 },
  { "title": "لوجه الله", "page": 235 },
  { "title": "كونوا زيناً لنا", "page": 237 },
  { "title": "من الظلمة إلى النور", "page": 240 },
  { "title": "واحة السكينة", "page": 244 },
  { "title": "الصمت الجميل", "page": 246 },
  { "title": "الأب الثاني", "page": 248 },
  { "title": "زكاة العلم", "page": 250 },
  { "title": "القلب الرحيم", "page": 252 },
  { "title": "المجاهد أمانه", "page": 255 },
  { "title": "علاقته بالسيد الشهيد الصدر", "page": 258 },
  { "title": "زاد الطريق إلى كربلاء", "page": 262 },
  { "title": "صلاة الجمعة", "page": 264 },
  { "title": "حب الوطن من الإيمان", "page": 267 },
  { "title": "الهم ينجلي عند رؤية صورة السيد الشهيد", "page": 270 },
  { "title": "عرفته القلوب", "page": 272 },
  { "title": "شهيد يذكر شهيد", "page": 275 },
  { "title": "خطوات على درب الخلود", "page": 280 },
  { "title": "شهادة وولادة", "page": 284 },
  { "title": "يقتفي أثر مولاه", "page": 287 },
  { "title": "حلمه يُدفن بين الشهداء", "page": 290 },
  { "title": "عزاءٌ عمَّ البلاد", "page": 292 },
  { "title": "رحل بصمت... فتكلمت الأفعال", "page": 294 },
  { "title": "الترابي", "page": 296 },
  { "title": "الإيمان على جدار الروح", "page": 299 },
  { "title": "أمنية لم تكتمل", "page": 303 },
  { "title": "دعوة تحت المطر", "page": 306 },
  { "title": "عطاء ممتد", "page": 308 },
  { "title": "من ثمار الولاء", "page": 310 },
  { "title": "الشفاء ببركة الشهداء", "page": 312 },
  { "title": "رحمة أب أمام أعين ولده", "page": 314 },
  { "title": "الصدق مع الله", "page": 316 },
  { "title": "دروس بعد الممات", "page": 318 },
  { "title": "اللطف الخفي", "page": 321 },
  { "title": "مأوى الحائرين", "page": 323 },
  { "title": "وجاهة الأرواح المخلصة", "page": 325 },
  { "title": "حضور بلا لقاء", "page": 327 },
  { "title": "ما قيل فيه", "page": 329 },
  { "title": "بعض فضائل الشهداء على لسان محمد وآله الأتقياء", "page": 353 },
  { "title": "الأرشيف الصوري", "page": 367 },
  { "title": "المحتويات", "page": 413 }
]
